cofffee/__init__.py
cofffee/accessors.py
cofffee/axis.py
cofffee/color.py
cofffee/graph_props.py
cofffee/grapher.py
cofffee/graphers.py
cofffee/palletts.py
cofffee/pyg.py
cofffee/test.py
cofffee/data/coffee.xlsx
cofffee/data/extra/icon.png
cofffee/data/fonts/DIN Condensed Bold.ttf
cofffee/data/fonts/Lulo Clean One Bold.otf
cofffee/data/fonts/Monoid-Retina.ttf
cofffee/data/fonts/fetchTitleFont.ttf
cofffee/extra/icon.png
cofffee-1.1.0.0.dist-info/LICENSE.txt
cofffee-1.1.0.0.dist-info/METADATA
cofffee-1.1.0.0.dist-info/WHEEL
cofffee-1.1.0.0.dist-info/top_level.txt
cofffee-1.1.0.0.dist-info/RECORD
